cutnorm/OptManiMulitBallGBB.py
cutnorm/__init__.py
cutnorm/compute.py
cutnorm/tools/__init__.py
cutnorm/tools/dbf_testing.py
cutnorm/tools/distort.py
cutnorm/tools/lpdist.py
cutnorm/tools/sbm.py
cutnorm-0.1.10.dist-info/licenses/LICENSE.txt
cutnorm-0.1.10.dist-info/METADATA
cutnorm-0.1.10.dist-info/WHEEL
cutnorm-0.1.10.dist-info/top_level.txt
cutnorm-0.1.10.dist-info/RECORD
