Metadata-Version: 2.4
Name: cutnorm
Version: 0.1.10
Summary: Cutnorm approximation via Gaussian Rounding and Optimization with Orthogonality Constraints
Home-page: https://github.com/pingkoc/cutnorm
Author: Ping-Ko Chiu, Peter Diao, Olewasanmi Koyejo
Author-email: pchiu5@illinois.edu, peter.z.diao@gmail.com, sanmi@illinois.edu
License: MIT
Classifier: Development Status :: 3 - Alpha
Classifier: Intended Audience :: Developers
Classifier: Topic :: Scientific/Engineering :: Information Analysis
Classifier: License :: OSI Approved :: MIT License
Classifier: Programming Language :: Python :: 3
Classifier: Programming Language :: Python :: 3.6
Classifier: Programming Language :: Python :: 3.7
Classifier: Programming Language :: Python :: 3.8
Classifier: Programming Language :: Python :: 3.9
Classifier: Programming Language :: Python :: 3.10
Classifier: Programming Language :: Python :: 3.11
Requires-Python: >=3.6
License-File: LICENSE.txt
Requires-Dist: numpy>=1.16.0
Requires-Dist: scikit-learn>=0.22.0
Requires-Dist: scipy>=1.3.0
Requires-Dist: numba>=0.45.0
Dynamic: author
Dynamic: author-email
Dynamic: classifier
Dynamic: description
Dynamic: home-page
Dynamic: license
Dynamic: license-file
Dynamic: requires-dist
Dynamic: requires-python
Dynamic: summary
